MANIFEST.in
README.md
setup.cfg
setup.py
/home/travis/build/yuyang0/pyshm/pyshm_ffi/allocator.c
/home/travis/build/yuyang0/pyshm/pyshm_ffi/buddy2.c
/home/travis/build/yuyang0/pyshm/pyshm_ffi/mempool.c
/home/travis/build/yuyang0/pyshm/pyshm_ffi/ring.c
pyshm/__init__.py
pyshm/mempool.py
pyshm/ring.py
pyshm/shm.py
pyshm.egg-info/PKG-INFO
pyshm.egg-info/SOURCES.txt
pyshm.egg-info/dependency_links.txt
pyshm.egg-info/requires.txt
pyshm.egg-info/top_level.txt
pyshm_ffi/allocator.c
pyshm_ffi/allocator.h
pyshm_ffi/atomic.h
pyshm_ffi/buddy2.c
pyshm_ffi/buddy2.h
pyshm_ffi/log.h
pyshm_ffi/mempool.c
pyshm_ffi/mempool.h
pyshm_ffi/pyshm_build.py
pyshm_ffi/pyshm_cdef.h
pyshm_ffi/pyshm_source.c
pyshm_ffi/ring.c
pyshm_ffi/ring.h
pyshm_ffi/utils.h