Metadata-Version: 1.1
Name: pyshm
Version: 0.0.1
Summary: python share memory library
Home-page: https://github.com/yuyang0/pyshm
Author: Yu Yang
Author-email: yyangplus@gmail.com
License: UNKNOWN
Platform: UNKNOWN
Classifier: Development Status :: 4 - Beta
Classifier: Programming Language :: Python :: 2
Classifier: Programming Language :: Python :: 3
Classifier: Programming Language :: Python :: Implementation :: PyPy
Classifier: License :: OSI Approved :: BSD License
